nukedatastore/__init__.py
nukedatastore-0.2.0.dist-info/DESCRIPTION.rst
nukedatastore-0.2.0.dist-info/LICENSE.txt
nukedatastore-0.2.0.dist-info/METADATA
nukedatastore-0.2.0.dist-info/RECORD
nukedatastore-0.2.0.dist-info/WHEEL
nukedatastore-0.2.0.dist-info/metadata.json
nukedatastore-0.2.0.dist-info/top_level.txt
