Metadata-Version: 2.0
Name: nukedatastore
Version: 0.2.0
Summary: A library for basic data persistence in Nuke
Home-page: https://github.com/florianeinfalt/nukedatastore
Author: Florian Einfalt
Author-email: info@florianeinfalt.de
License: Apache 2.0
Platform: UNKNOWN
Classifier: Development Status :: 3 - Alpha
Classifier: Intended Audience :: Developers
Classifier: Natural Language :: English
Classifier: Topic :: Software Development :: Build Tools
Classifier: License :: OSI Approved :: Apache Software License
Classifier: Programming Language :: Python
Classifier: Programming Language :: Python :: 2.6
Classifier: Programming Language :: Python :: 2.7
Classifier: Programming Language :: Python :: Implementation :: CPython
Requires-Dist: deepdiff
Requires-Dist: nukeuuid
